MANIFEST.in
mypy.ini
setup.cfg
setup.py
./mypy.ini
./build/lib/persimmon/background.png
./build/lib/persimmon/border.png
./build/lib/persimmon/cog.png
./build/lib/persimmon/config.ini
./build/lib/persimmon/play.png
./build/lib/persimmon/play_blue.png
./build/lib/persimmon/view/blackboard.kv
./build/lib/persimmon/view/view.kv
./build/lib/persimmon/view/blocks/block.kv
./build/lib/persimmon/view/blocks/crossvalidationblock.kv
./build/lib/persimmon/view/blocks/csvinblock.kv
./build/lib/persimmon/view/blocks/csvoutblock.kv
./build/lib/persimmon/view/blocks/dictblock.kv
./build/lib/persimmon/view/blocks/fitblock.kv
./build/lib/persimmon/view/blocks/gridsearchblock.kv
./build/lib/persimmon/view/blocks/knnblock.kv
./build/lib/persimmon/view/blocks/predictblock.kv
./build/lib/persimmon/view/blocks/printblock.kv
./build/lib/persimmon/view/blocks/randomforestblock.kv
./build/lib/persimmon/view/blocks/sgdblock.kv
./build/lib/persimmon/view/blocks/smart_bubble.kv
./build/lib/persimmon/view/blocks/svmblock.kv
./build/lib/persimmon/view/blocks/tenfoldblock.kv
./build/lib/persimmon/view/blocks/tssplitblock.kv
./build/lib/persimmon/view/pins/circularbutton.kv
./build/lib/persimmon/view/pins/inpin.kv
./build/lib/persimmon/view/pins/outpin.kv
./build/lib/persimmon/view/pins/pin.kv
./build/lib/persimmon/view/util/filedialog.kv
./build/lib/persimmon/view/util/notification.kv
./build/lib/persimmon/view/util/play_button.kv
./docs/images/china.png
./docs/images/familiarity.png
./docs/images/fdi.png
./docs/images/final_aspect.png
./docs/images/interface.png
./docs/images/iter2.png
./docs/images/iter3.png
./docs/images/score.png
./docs/images/sketch_1.png
./docs/images/sketch_2.png
./docs/images/unreal.png
./env/lib/python3.6/site-packages/kivy/data/style.kv
./env/lib/python3.6/site-packages/kivy/data/glsl/default.png
./env/lib/python3.6/site-packages/kivy/data/images/cursor.png
./env/lib/python3.6/site-packages/kivy/data/images/defaulttheme-0.png
persimmon.egg-info/PKG-INFO
persimmon.egg-info/SOURCES.txt
persimmon.egg-info/dependency_links.txt
persimmon.egg-info/entry_points.txt
persimmon.egg-info/not-zip-safe
persimmon.egg-info/requires.txt
persimmon.egg-info/top_level.txt
